colorbar/__init__.py
colorbar/cbar.py
colorbar/data/DejaVuSans.ttf
colorbar/utils.py
colorbar-0.2.0.dist-info/LICENSE
colorbar-0.2.0.dist-info/METADATA
colorbar-0.2.0.dist-info/WHEEL
colorbar-0.2.0.dist-info/RECORD
