Metadata-Version: 2.1
Name: colorbar
Version: 0.2.0
Summary: Colorbar in Python. Fast and lightweight!
Home-page: https://github.com/codingfisch/colorbar
License: MIT
Author: codingfisch
Author-email: l_fisc17@wwu.de
Requires-Python: >=3.9,<4.0
Classifier: Intended Audience :: Science/Research
Classifier: License :: OSI Approved :: MIT License
Classifier: Operating System :: OS Independent
Classifier: Programming Language :: Python :: 3
Classifier: Programming Language :: Python :: 3.9
Classifier: Programming Language :: Python :: 3.10
Classifier: Programming Language :: Python :: 3.11
Classifier: Programming Language :: Python :: 3.12
Classifier: Programming Language :: Python :: 3.13
Requires-Dist: cmap
Requires-Dist: numpy
Requires-Dist: pillow
Requires-Dist: pycairo
Project-URL: Repository, https://github.com/codingfisch/colorbar
